schulze_voting/__init__.py
schulze_voting/schulze_voting.py
schulze_voting-0.1.1.dist-info/DESCRIPTION.rst
schulze_voting-0.1.1.dist-info/METADATA
schulze_voting-0.1.1.dist-info/RECORD
schulze_voting-0.1.1.dist-info/WHEEL
schulze_voting-0.1.1.dist-info/metadata.json
schulze_voting-0.1.1.dist-info/top_level.txt
