Metadata-Version: 2.0
Name: schulze-voting
Version: 0.1.1
Summary: A python implementation for Schulze votings with the possibility to have weighted votes.
Home-page: https://github.com/FabianWe/schulze_voting
Author: Fabian Wenzelmann
Author-email: fabianwen@posteo.eu
License: MIT
Keywords: voting schulze
Platform: UNKNOWN
Requires-Dist: pytest
